AUTHORS
CHANGES.rst
LICENSE
MANIFEST.in
README.rst
setup.py
anonymizer/__init__.py
anonymizer/base.py
anonymizer/introspect.py
anonymizer/models.py
anonymizer/replacers.py
anonymizer/test_settings.py
anonymizer/management/__init__.py
anonymizer/management/commands/__init__.py
anonymizer/management/commands/anonymize_data.py
anonymizer/management/commands/create_anonymizers.py
anonymizer/tests/__init__.py
anonymizer/tests/models.py
django_anonymizer_compat.egg-info/PKG-INFO
django_anonymizer_compat.egg-info/SOURCES.txt
django_anonymizer_compat.egg-info/dependency_links.txt
django_anonymizer_compat.egg-info/requires.txt
django_anonymizer_compat.egg-info/top_level.txt
docs/Makefile
docs/anonymizers.rst
docs/commands.rst
docs/conf.py
docs/djangofaker.rst
docs/index.rst
docs/install.rst
docs/overview.rst
docs/replacers.rst