Metadata-Version: 1.1
Name: django-anonymizer-compat
Version: 0.4
Summary: App to anonymize data in Django models.
Home-page: https://bitbucket.org/izqs/django-anonymizer
Author: Luke Plant
Author-email: L.Plant.98@cantab.net
License: MIT
Keywords: django data database anonymize private
Platform: UNKNOWN
Classifier: Development Status :: 4 - Beta
Classifier: Environment :: Web Environment
Classifier: Environment :: Console
Classifier: Intended Audience :: Developers
Classifier: License :: OSI Approved :: MIT License
Classifier: Operating System :: OS Independent
Classifier: Programming Language :: Python
Classifier: Programming Language :: Python :: 2.5
Classifier: Programming Language :: Python :: 2.6
Classifier: Programming Language :: Python :: 2.7
Classifier: Framework :: Django
Classifier: Topic :: Software Development :: Testing
Classifier: Topic :: Database
